{"namedChunkGroups":{"polyfill":{"name":"polyfill","assets":[{"name":"webpack-runtime-6c5ff8d74ffcb30cffc6.js","size":5111},{"name":"polyfill-72b219bae196683411be.js","size":82649}],"filteredAssets":0,"assetsSize":87760,"filteredAuxiliaryAssets":2,"auxiliaryAssetsSize":221544},"app":{"name":"app","assets":[{"name":"webpack-runtime-6c5ff8d74ffcb30cffc6.js","size":5111},{"name":"styles.2f92a14e62178bee8d10.css","size":203971},{"name":"framework-2863138be6d134764ab2.js","size":22584},{"name":"app-2fc1b97060bef632d5a3.js","size":69739}],"filteredAssets":0,"assetsSize":301405,"filteredAuxiliaryAssets":3,"auxiliaryAssetsSize":400238},"component---src-pages-404-tsx":{"name":"component---src-pages-404-tsx","assets":[{"name":"commons-785797e829b15682d0a8.js","size":149557},{"name":"component---src-pages-404-tsx-6b76c8e446087481dddf.js","size":522}],"filteredAssets":0,"assetsSize":150079,"filteredAuxiliaryAssets":2,"auxiliaryAssetsSize":564503},"component---src-pages-blog-tsx":{"name":"component---src-pages-blog-tsx","assets":[{"name":"1bfc9850-05a1decf39fcb31ad80d.js","size":5784},{"name":"commons-785797e829b15682d0a8.js","size":149557},{"name":"component---src-pages-blog-tsx-37fb10f2800ace7baf15.js","size":5272}],"filteredAssets":0,"assetsSize":160613,"filteredAuxiliaryAssets":3,"auxiliaryAssetsSize":2044289},"component---src-pages-index-tsx":{"name":"component---src-pages-index-tsx","assets":[{"name":"1bfc9850-05a1decf39fcb31ad80d.js","size":5784},{"name":"commons-785797e829b15682d0a8.js","size":149557},{"name":"component---src-pages-index-tsx-129dd79ef8a770d498b5.js","size":9097}],"filteredAssets":0,"assetsSize":164438,"filteredAuxiliaryAssets":3,"auxiliaryAssetsSize":2048256},"component---src-templates-blog-post-tsx":{"name":"component---src-templates-blog-post-tsx","assets":[{"name":"styles.2f92a14e62178bee8d10.css","size":203971},{"name":"1bfc9850-05a1decf39fcb31ad80d.js","size":5784},{"name":"commons-785797e829b15682d0a8.js","size":149557},{"name":"component---src-templates-blog-post-tsx-fcb7ceea0a80b9d8c9b9.js","size":914724}],"filteredAssets":0,"assetsSize":1274036,"filteredAuxiliaryAssets":3,"auxiliaryAssetsSize":3830964}},"assetsByChunkName":{"polyfill":["webpack-runtime-6c5ff8d74ffcb30cffc6.js","polyfill-72b219bae196683411be.js"],"app":["webpack-runtime-6c5ff8d74ffcb30cffc6.js","styles.2f92a14e62178bee8d10.css","framework-2863138be6d134764ab2.js","app-2fc1b97060bef632d5a3.js"],"component---src-pages-404-tsx":["commons-785797e829b15682d0a8.js","component---src-pages-404-tsx-6b76c8e446087481dddf.js"],"component---src-pages-blog-tsx":["1bfc9850-05a1decf39fcb31ad80d.js","commons-785797e829b15682d0a8.js","component---src-pages-blog-tsx-37fb10f2800ace7baf15.js"],"component---src-pages-index-tsx":["1bfc9850-05a1decf39fcb31ad80d.js","commons-785797e829b15682d0a8.js","component---src-pages-index-tsx-129dd79ef8a770d498b5.js"],"component---src-templates-blog-post-tsx":["styles.2f92a14e62178bee8d10.css","1bfc9850-05a1decf39fcb31ad80d.js","commons-785797e829b15682d0a8.js","component---src-templates-blog-post-tsx-fcb7ceea0a80b9d8c9b9.js"]},"childAssetsByChunkName":{}}