{"namedChunkGroups":{"polyfill":{"name":"polyfill","assets":[{"name":"webpack-runtime-5605a18c1059beb98140.js","size":5138},{"name":"polyfill-72b219bae196683411be.js","size":82649}],"filteredAssets":0,"assetsSize":87787,"filteredAuxiliaryAssets":2,"auxiliaryAssetsSize":221589},"app":{"name":"app","assets":[{"name":"webpack-runtime-5605a18c1059beb98140.js","size":5138},{"name":"styles.a93e5ddba4d4235b209e.css","size":205304},{"name":"framework-58bf812a13a0f931603c.js","size":22076},{"name":"app-18d6cd0bd2159b299af4.js","size":70265}],"filteredAssets":0,"assetsSize":302783,"filteredAuxiliaryAssets":3,"auxiliaryAssetsSize":401592},"component---src-pages-404-tsx":{"name":"component---src-pages-404-tsx","assets":[{"name":"commons-785797e829b15682d0a8.js","size":149557},{"name":"component---src-pages-404-tsx-6b76c8e446087481dddf.js","size":522}],"filteredAssets":0,"assetsSize":150079,"filteredAuxiliaryAssets":2,"auxiliaryAssetsSize":564503},"component---src-pages-blog-tsx":{"name":"component---src-pages-blog-tsx","assets":[{"name":"1bfc9850-05a1decf39fcb31ad80d.js","size":5784},{"name":"commons-785797e829b15682d0a8.js","size":149557},{"name":"component---src-pages-blog-tsx-37fb10f2800ace7baf15.js","size":5272}],"filteredAssets":0,"assetsSize":160613,"filteredAuxiliaryAssets":3,"auxiliaryAssetsSize":2044289},"component---src-pages-index-tsx":{"name":"component---src-pages-index-tsx","assets":[{"name":"1bfc9850-05a1decf39fcb31ad80d.js","size":5784},{"name":"commons-785797e829b15682d0a8.js","size":149557},{"name":"component---src-pages-index-tsx-129dd79ef8a770d498b5.js","size":9097}],"filteredAssets":0,"assetsSize":164438,"filteredAuxiliaryAssets":3,"auxiliaryAssetsSize":2048256},"component---src-templates-blog-post-tsx":{"name":"component---src-templates-blog-post-tsx","assets":[{"name":"styles.a93e5ddba4d4235b209e.css","size":205304},{"name":"1bfc9850-05a1decf39fcb31ad80d.js","size":5784},{"name":"commons-785797e829b15682d0a8.js","size":149557},{"name":"component---src-templates-blog-post-tsx-fcb7ceea0a80b9d8c9b9.js","size":914724}],"filteredAssets":0,"assetsSize":1275369,"filteredAuxiliaryAssets":3,"auxiliaryAssetsSize":3830964}},"assetsByChunkName":{"polyfill":["webpack-runtime-5605a18c1059beb98140.js","polyfill-72b219bae196683411be.js"],"app":["webpack-runtime-5605a18c1059beb98140.js","styles.a93e5ddba4d4235b209e.css","framework-58bf812a13a0f931603c.js","app-18d6cd0bd2159b299af4.js"],"component---src-pages-404-tsx":["commons-785797e829b15682d0a8.js","component---src-pages-404-tsx-6b76c8e446087481dddf.js"],"component---src-pages-blog-tsx":["1bfc9850-05a1decf39fcb31ad80d.js","commons-785797e829b15682d0a8.js","component---src-pages-blog-tsx-37fb10f2800ace7baf15.js"],"component---src-pages-index-tsx":["1bfc9850-05a1decf39fcb31ad80d.js","commons-785797e829b15682d0a8.js","component---src-pages-index-tsx-129dd79ef8a770d498b5.js"],"component---src-templates-blog-post-tsx":["styles.a93e5ddba4d4235b209e.css","1bfc9850-05a1decf39fcb31ad80d.js","commons-785797e829b15682d0a8.js","component---src-templates-blog-post-tsx-fcb7ceea0a80b9d8c9b9.js"]},"childAssetsByChunkName":{}}